pymewc/__init__.py
pymewc-0.1.6.dist-info/LICENSE
pymewc-0.1.6.dist-info/METADATA
pymewc-0.1.6.dist-info/WHEEL
pymewc-0.1.6.dist-info/top_level.txt
pymewc-0.1.6.dist-info/RECORD
