Metadata-Version: 2.1
Name: pymewc
Version: 0.1.6
Summary: Microcontroller and python interface
Home-page: UNKNOWN
Author: Rithic C H
Author-email: gr8rithic@gmail.com
License: UNKNOWN
Keywords: python,IoT,microcontroller,Arduino,Text-to-speech
Platform: UNKNOWN
Classifier: Development Status :: 4 - Beta
Classifier: Intended Audience :: Developers
Classifier: Intended Audience :: Education
Classifier: Intended Audience :: Science/Research
Classifier: Intended Audience :: Telecommunications Industry
Classifier: License :: OSI Approved :: MIT License
Classifier: Programming Language :: Python :: 3
Classifier: Operating System :: Unix
Classifier: Operating System :: MacOS :: MacOS X
Classifier: Operating System :: Microsoft :: Windows
Requires-Dist: matplotlib
Requires-Dist: numpy
Requires-Dist: pyfirmata2
Requires-Dist: pyserial
Requires-Dist: pyttsx3
Requires-Dist: setuptools
